jaraco/nxt/__init__.py
jaraco/nxt/_enum.py
jaraco/nxt/controller.py
jaraco/nxt/messages.py
jaraco/nxt/routine.py
jaraco.nxt-2.2.1.dist-info/LICENSE
jaraco.nxt-2.2.1.dist-info/METADATA
jaraco.nxt-2.2.1.dist-info/WHEEL
jaraco.nxt-2.2.1.dist-info/entry_points.txt
jaraco.nxt-2.2.1.dist-info/top_level.txt
jaraco.nxt-2.2.1.dist-info/RECORD
